mcp_metal_price/__init__.py
mcp_metal_price/__main__.py
mcp_metal_price/server.py
mcp_metal_price-0.0.4.dist-info/licenses/LICENSE
mcp_metal_price-0.0.4.dist-info/METADATA
mcp_metal_price-0.0.4.dist-info/WHEEL
mcp_metal_price-0.0.4.dist-info/entry_points.txt
mcp_metal_price-0.0.4.dist-info/top_level.txt
mcp_metal_price-0.0.4.dist-info/RECORD
