Metadata-Version: 2.4
Name: mcp_metal_price
Version: 0.0.4
Summary: An MCP server for metal price information
Author-email: danielshih <dog830228@gmail.com>
Project-URL: Source, https://github.com/isdaniel/mcp-metal-price
Requires-Python: >=3.13
License-File: LICENSE
Requires-Dist: mcp>=1.0.0
Requires-Dist: requests>=2.31.0
Dynamic: license-file
